captametropolis/__cli__.py
captametropolis/__init__.py
captametropolis/__version__.py
captametropolis/errors.py
captametropolis/segment_parser.py
captametropolis/text_drawer.py
captametropolis/transcriber.py
captametropolis/utils.py
captametropolis/assets/fonts/Bangers-Regular-LICENSE.txt
captametropolis/assets/fonts/Bangers-Regular.ttf
captametropolis/assets/fonts/Knewave-Regular-LICENSE.txt
captametropolis/assets/fonts/Knewave-Regular.ttf
captametropolis/assets/fonts/PoetsenOne-Regular-LICENSE.txt
captametropolis/assets/fonts/PoetsenOne-Regular.ttf
captametropolis-1.1.3.dist-info/licenses/LICENSE
captametropolis-1.1.3.dist-info/METADATA
captametropolis-1.1.3.dist-info/WHEEL
captametropolis-1.1.3.dist-info/entry_points.txt
captametropolis-1.1.3.dist-info/top_level.txt
captametropolis-1.1.3.dist-info/RECORD
