Metadata-Version: 2.4
Name: captametropolis
Version: 1.1.3
Summary: Add Automatic Captions to YouTube Shorts with AI
Home-page: https://github.com/AppSolves/captametropolis
Author: Original: Unconventional Coding | This Fork: AppSolves
Author-email: unconventionalcoding@gmail.com
Maintainer: AppSolves
Maintainer-email: contact@appsolves.dev
License: MIT
License-File: LICENSE
Requires-Dist: moviepy<2.0.0
Requires-Dist: pillow
Requires-Dist: openai
Requires-Dist: setuptools-rust
Requires-Dist: torch
Requires-Dist: numpy
Requires-Dist: ffmpeg-python
Requires-Dist: opencv-python
Requires-Dist: fonttools
Requires-Dist: lxml
Requires-Dist: typer
Requires-Dist: rich
Provides-Extra: local
Requires-Dist: openai-whisper; extra == "local"
Dynamic: author
Dynamic: author-email
Dynamic: description
Dynamic: description-content-type
Dynamic: home-page
Dynamic: license
Dynamic: license-file
Dynamic: maintainer
Dynamic: maintainer-email
Dynamic: provides-extra
Dynamic: requires-dist
Dynamic: summary
